rhoshift/__init__.py
rhoshift/main.py
rhoshift/cli/__init__.py
rhoshift/cli/args.py
rhoshift/cli/commands.py
rhoshift/logger/__init__.py
rhoshift/logger/logger.py
rhoshift/rhoai_upgrade_matrix/__init__.py
rhoshift/rhoai_upgrade_matrix/cli.py
rhoshift/rhoai_upgrade_matrix/run_matrix.py
rhoshift/scripts/run_upgrade_matrix.sh
rhoshift/scripts/cleanup/cleanup_all.sh
rhoshift/utils/__init__.py
rhoshift/utils/constants.py
rhoshift/utils/health_monitor.py
rhoshift/utils/resilience.py
rhoshift/utils/stability_coordinator.py
rhoshift/utils/utils.py
rhoshift/utils/operator/__init__.py
rhoshift/utils/operator/cleanup.py
rhoshift/utils/operator/enhanced_operator.py
rhoshift/utils/operator/operator.py
rhoshift-0.1.7.4.dist-info/licenses/LICENSE
rhoshift-0.1.7.4.dist-info/METADATA
rhoshift-0.1.7.4.dist-info/WHEEL
rhoshift-0.1.7.4.dist-info/entry_points.txt
rhoshift-0.1.7.4.dist-info/top_level.txt
rhoshift-0.1.7.4.dist-info/RECORD
