Metadata-Version: 2.4
Name: rhoshift
Version: 0.1.7.4
Summary: RHOAI tool kit for managing and upgrading RHOAI
Author: Milind Waykole
License:                                  Apache License
Project-URL: Homepage, https://github.com/mwaykole/O
Project-URL: Bug Tracker, https://github.com/mwaykole/O/issues
Keywords: rhoai,openshift,upgrade,toolkit,red hat
Classifier: Development Status :: 4 - Beta
Classifier: Intended Audience :: Developers
Classifier: Intended Audience :: System Administrators
Classifier: Programming Language :: Python :: 3
Classifier: Programming Language :: Python :: 3.8
Classifier: Programming Language :: Python :: 3.9
Classifier: Programming Language :: Python :: 3.10
Classifier: Programming Language :: Python :: 3.11
Classifier: Programming Language :: Python :: 3.12
Classifier: License :: OSI Approved :: Apache Software License
Classifier: Operating System :: OS Independent
Requires-Python: >=3.8
License-File: LICENSE
Requires-Dist: boto3<1.39.0,>=1.26.0
Requires-Dist: botocore<1.39.0,>=1.29.0
Requires-Dist: kubernetes<34.0.0,>=26.1.0
Requires-Dist: openshift-client<3.0.0,>=1.0.2
Requires-Dist: python-dotenv<2.0.0,>=1.0.0
Requires-Dist: requests<3.0.0,>=2.31.0
Requires-Dist: urllib3<3.0.0,>=1.26.0
Requires-Dist: colorlog<7.0.0,>=6.7.0
Requires-Dist: pyfiglet<2.0.0,>=0.8.post1
Requires-Dist: setuptools<76.0.0,>=61.0
Requires-Dist: typing-extensions<5.0.0,>=4.7.0
Provides-Extra: test
Requires-Dist: pytest; extra == "test"
Requires-Dist: pytest-cov; extra == "test"
Provides-Extra: dev
Requires-Dist: ruff>=0.13.0; extra == "dev"
Requires-Dist: pre-commit>=3.3.0; extra == "dev"
Requires-Dist: build; extra == "dev"
Requires-Dist: mypy>=1.18.0; extra == "dev"
Requires-Dist: gitleaks; extra == "dev"
Requires-Dist: detect-secrets; extra == "dev"
Requires-Dist: types-PyYAML; extra == "dev"
Requires-Dist: types-requests; extra == "dev"
Dynamic: license-file
